skytemple_randomizer/__init__.py
skytemple_randomizer/config.py
skytemple_randomizer/data_dir.py
skytemple_randomizer/export_quiz_xml.py
skytemple_randomizer/lists.py
skytemple_randomizer/main.py
skytemple_randomizer/py.typed
skytemple_randomizer/randomizer_thread.py
skytemple_randomizer/spritecollab.py
skytemple_randomizer/status.py
skytemple_randomizer/string_provider.py
skytemple_randomizer/data/default.json
skytemple_randomizer/data/duskako_happy.png
skytemple_randomizer/data/duskako_neutral.png
skytemple_randomizer/data/duskako_sad.png
skytemple_randomizer/data/vanilla_questions.xml
skytemple_randomizer/data/fixed_floor_layouts/0.txt
skytemple_randomizer/data/fixed_floor_layouts/1.txt
skytemple_randomizer/data/fixed_floor_layouts/10.txt
skytemple_randomizer/data/fixed_floor_layouts/100.txt
skytemple_randomizer/data/fixed_floor_layouts/101.txt
skytemple_randomizer/data/fixed_floor_layouts/102.txt
skytemple_randomizer/data/fixed_floor_layouts/103.txt
skytemple_randomizer/data/fixed_floor_layouts/104.txt
skytemple_randomizer/data/fixed_floor_layouts/105.txt
skytemple_randomizer/data/fixed_floor_layouts/106.txt
skytemple_randomizer/data/fixed_floor_layouts/107.txt
skytemple_randomizer/data/fixed_floor_layouts/108.txt
skytemple_randomizer/data/fixed_floor_layouts/109.txt
skytemple_randomizer/data/fixed_floor_layouts/11.txt
skytemple_randomizer/data/fixed_floor_layouts/110.txt
skytemple_randomizer/data/fixed_floor_layouts/111.txt
skytemple_randomizer/data/fixed_floor_layouts/112.txt
skytemple_randomizer/data/fixed_floor_layouts/113.txt
skytemple_randomizer/data/fixed_floor_layouts/114.txt
skytemple_randomizer/data/fixed_floor_layouts/115.txt
skytemple_randomizer/data/fixed_floor_layouts/116.txt
skytemple_randomizer/data/fixed_floor_layouts/117.txt
skytemple_randomizer/data/fixed_floor_layouts/118.txt
skytemple_randomizer/data/fixed_floor_layouts/119.txt
skytemple_randomizer/data/fixed_floor_layouts/12.txt
skytemple_randomizer/data/fixed_floor_layouts/120.txt
skytemple_randomizer-2.2.0.dist-info/LICENSE
skytemple_randomizer-2.2.0.dist-info/METADATA
skytemple_randomizer-2.2.0.dist-info/WHEEL
skytemple_randomizer-2.2.0.dist-info/entry_points.txt
skytemple_randomizer-2.2.0.dist-info/top_level.txt
skytemple_randomizer-2.2.0.dist-info/RECORD
