Metadata-Version: 2.1
Name: skytemple-randomizer
Version: 2.2.0
Summary: Randomizer GUI to randomize the ROM of Pokémon Mystery Dungeon Explorers of Sky
Author-email: "Marco \"Capypara\" Köpcke" <hello@capypara.de>
License: GPL-3.0-or-later
Project-URL: Homepage, https://skytemple.org
Project-URL: Announcements, https://blog.skytemple.org
Project-URL: Documentation, https://wiki.skytemple.org
Project-URL: Downloads, https://download.skytemple.org/randomizer
Project-URL: Changelog, https://download.skytemple.org/randomizer
Project-URL: Repository, https://github.com/SkyTemple/skytemple-randomizer.git
Project-URL: Issues, https://github.com/SkyTemple/skytemple-randomizer/issues
Project-URL: Discord, https://discord.gg/skytemple
Keywords: rom-hacking,game-modding,skytemple,gtk,randomizer
Classifier: Development Status :: 4 - Beta
Classifier: Programming Language :: Python
Classifier: License :: OSI Approved :: GNU General Public License v3 or later (GPLv3+)
Classifier: Programming Language :: Python :: 3.10
Classifier: Programming Language :: Python :: 3.11
Classifier: Programming Language :: Python :: 3.12
Classifier: Programming Language :: Python :: 3.13
Requires-Python: >=3.10
License-File: LICENSE
Requires-Dist: click<9.0,>=8.1
Requires-Dist: ndspy<5.0.0,>=3.0.0
Requires-Dist: skytemple-files[spritecollab]<1.9.0,>=1.8.5
Requires-Dist: explorerscript>=0.2.2
Requires-Dist: skytemple-icons<1.9.0,>=1.3.2
Requires-Dist: packaging
Provides-Extra: gtk
Requires-Dist: pygobject>=3.44.0; extra == "gtk"
